{
  "arch": "x64",
  "archive_type": "tar.gz",
  "filename": "zulu13.28.11-ca-jre13.0.1-macosx_x64.tar.gz",
  "java_version": "13.0.1",
  "md5": "e4c94dddc7085a4bde81713ba4645401",
  "md5_file": "zulu13.28.11-ca-jre13.0.1-macosx_x64.tar.gz.md5",
  "os": "macosx",
  "release_type": "ca",
  "sha1": "e6e09b5f27259faa05a28c2dda1b4058bd78025c",
  "sha1_file": "zulu13.28.11-ca-jre13.0.1-macosx_x64.tar.gz.sha1",
  "sha256": "ed9c32de909cbe73d608907b33ae806b5354056cd7f09fff77d0180fac69332b",
  "sha256_file": "zulu13.28.11-ca-jre13.0.1-macosx_x64.tar.gz.sha256",
  "sha512": "d7c8233008ab580bde0ed6c1de3262e883dc6ab541a79eeca3d18f17d264b2ff0684ea590b482761b253b4e128429e92d161587a43c9c4df9feb98aa69d5d733",
  "sha512_file": "zulu13.28.11-ca-jre13.0.1-macosx_x64.tar.gz.sha512",
  "url": "https://static.azul.com/zulu/bin/zulu13.28.11-ca-jre13.0.1-macosx_x64.tar.gz",
  "variant": "jre",
  "version": "13.28.11"
}
{
  "arch": "x64",
  "archive_type": "zip",
  "filename": "zulu13.28.11-ca-jre13.0.1-macosx_x64.zip",
  "java_version": "13.0.1",
  "md5": "3c3f6a8d45b074a9adf5790010407ea2",
  "md5_file": "zulu13.28.11-ca-jre13.0.1-macosx_x64.zip.md5",
  "os": "macosx",
  "release_type": "ca",
  "sha1": "cbf41e15e9d92434aa0fa6b17255874bd8034ef4",
  "sha1_file": "zulu13.28.11-ca-jre13.0.1-macosx_x64.zip.sha1",
  "sha256": "7d300463c2d94c7a814c46a5dcb1df3b0d5b15ad8db3061e8f81d1457069538a",
  "sha256_file": "zulu13.28.11-ca-jre13.0.1-macosx_x64.zip.sha256",
  "sha512": "952a59355edcf8b0418873fd6e48ef9652eec90fef17ab0547fcf460b00ced8fa45cbfb3f5b3ff7b0fdd82dee6dc034e4921235353e5c4ca9141046f0c440baf",
  "sha512_file": "zulu13.28.11-ca-jre13.0.1-macosx_x64.zip.sha512",
  "url": "https://static.azul.com/zulu/bin/zulu13.28.11-ca-jre13.0.1-macosx_x64.zip",
  "variant": "jre",
  "version": "13.28.11"
}
{
  "arch": "x64",
  "archive_type": "dmg",
  "filename": "zulu13.29.9-ca-jre13.0.2-macosx_x64.dmg",
  "java_version": "13.0.2",
  "md5": "99515ea24694d1cce911cfb5e9823eab",
  "md5_file": "zulu13.29.9-ca-jre13.0.2-macosx_x64.dmg.md5",
  "os": "macosx",
  "release_type": "ca",
  "sha1": "a5554dc494132cf8aed1c37ac6a3eb3a28386045",
  "sha1_file": "zulu13.29.9-ca-jre13.0.2-macosx_x64.dmg.sha1",
  "sha256": "69e1731d82dab4118f38143ad48f8b988046f822cf2df5eeab81f291c2bde3fa",
  "sha256_file": "zulu13.29.9-ca-jre13.0.2-macosx_x64.dmg.sha256",
  "sha512": "3c40874393cf8e299d6f5617a3bdfdf6be7f1916b6c4db08a15ffe464dd4bf42fc94b51bee50ad9e4e3759f97ded0740b9d7179de73ffe32c5865391ff1c7555",
  "sha512_file": "zulu13.29.9-ca-jre13.0.2-macosx_x64.dmg.sha512",
  "url": "https://static.azul.com/zulu/bin/zulu13.29.9-ca-jre13.0.2-macosx_x64.dmg",
  "variant": "jre",
  "version": "13.29.9"
}
{
  "arch": "x64",
  "archive_type": "tar.gz",
  "filename": "zulu13.29.9-ca-jre13.0.2-macosx_x64.tar.gz",
  "java_version": "13.0.2",
  "md5": "11b2540706d9597fd99a42e3d4033069",
  "md5_file": "zulu13.29.9-ca-jre13.0.2-macosx_x64.tar.gz.md5",
  "os": "macosx",
  "release_type": "ca",
  "sha1": "eb7d184acf517572ce9e98d09e4ea94c5dbe3d8e",
  "sha1_file": "zulu13.29.9-ca-jre13.0.2-macosx_x64.tar.gz.sha1",
  "sha256": "5542232e7edc721fcca04e4e734f8545e931172a2db68aee9e4cdc4c670079a6",
  "sha256_file": "zulu13.29.9-ca-jre13.0.2-macosx_x64.tar.gz.sha256",
  "sha512": "bde7664cbdd199700e6a104694756346a301842dcc2381b87aa2739fa3f06b248574cc310d4c705e79e747600b95459f46f8d2967fb8253f54f365dd0d6a69fd",
  "sha512_file": "zulu13.29.9-ca-jre13.0.2-macosx_x64.tar.gz.sha512",
  "url": "https://static.azul.com/zulu/bin/zulu13.29.9-ca-jre13.0.2-macosx_x64.tar.gz",
  "variant": "jre",
  "version": "13.29.9"
}
{
  "arch": "x64",
  "archive_type": "zip",
  "filename": "zulu13.29.9-ca-jre13.0.2-macosx_x64.zip",
  "java_version": "13.0.2",
  "md5": "4413ba14fe271c56273fad64f94a31bd",
  "md5_file": "zulu13.29.9-ca-jre13.0.2-macosx_x64.zip.md5",
  "os": "macosx",
  "release_type": "ca",
  "sha1": "ef33d250379334067f94fe232a7893468c6508a1",
  "sha1_file": "zulu13.29.9-ca-jre13.0.2-macosx_x64.zip.sha1",
  "sha256": "c1b2e895b6858f273c08a4ecdd1d7cb7e1dfc37f175964a43ca601f7bcfe681b",
  "sha256_file": "zulu13.29.9-ca-jre13.0.2-macosx_x64.zip.sha256",
  "sha512": "06af1f75b7c0809e55523348cb700632fb4b310b1dbd4fa1897e89f452c4792c18c6882811e01ebc9902a7a6105b3149e1bd209e322be480e6cbefca7295c20d",
  "sha512_file": "zulu13.29.9-ca-jre13.0.2-macosx_x64.zip.sha512",
  "url": "https://static.azul.com/zulu/bin/zulu13.29.9-ca-jre13.0.2-macosx_x64.zip",
  "variant": "jre",
  "version": "13.29.9"
}
